LICENSE.txt
MANIFEST.in
NEWS.txt
README.txt
setup.py
pygoo/__init__.py
pygoo/abstractdirectedgraph.py
pygoo/abstractnode.py
pygoo/baseobject.py
pygoo/memoryobjectgraph.py
pygoo/memoryobjectnode.py
pygoo/neo.py
pygoo/neo4jobjectgraph.py
pygoo/neo4jobjectnode.py
pygoo/objectgraph.py
pygoo/objectnode.py
pygoo/ontology.py
pygoo/utils.py
pygoo.egg-info/PKG-INFO
pygoo.egg-info/SOURCES.txt
pygoo.egg-info/dependency_links.txt
pygoo.egg-info/entry_points.txt
pygoo.egg-info/not-zip-safe
pygoo.egg-info/top_level.txt
test/test_advancedgraph.py
test/test_basicnode.py
test/test_datamodel.py
test/test_inheritance.py
test/test_memory.py