Metadata-Version: 1.0
Name: pygoo
Version: 0.1.2
Summary: PyGoo is an Object-Graph mapper, similar to SQLAlchemy but for graph DBs
Home-page: http://gitorious.org/pygoo
Author: Nicolas Wack
Author-email: wackou@gmail.com
License: GPLv3
Keywords: pygoo object graph mapper
Platform: UNKNOWN
